panda3d_analyze/__init__.py
p3d_analyze-1.0.0.dist-info/LICENSE
p3d_analyze-1.0.0.dist-info/METADATA
p3d_analyze-1.0.0.dist-info/WHEEL
p3d_analyze-1.0.0.dist-info/top_level.txt
p3d_analyze-1.0.0.dist-info/RECORD
