Metadata-Version: 2.1
Name: p3d-analyze
Version: 1.0.0
Summary: Panda3D module that provides simplified stat collection and analysis
Home-page: https://github.com/NxtStudios/p3d-analyze
Author: Jordan Maxwell
Maintainer: Jordan Maxwell
License: MIT
Platform: UNKNOWN
Classifier: Programming Language :: Python :: 3
License-File: LICENSE
